efootprint/__init__.py
efootprint/abstract_modeling_classes/__init__.py
efootprint/abstract_modeling_classes/aggregation_utils.py
efootprint/abstract_modeling_classes/contextual_modeling_object_attribute.py
efootprint/abstract_modeling_classes/empty_explainable_object.py
efootprint/abstract_modeling_classes/explainable_dict.py
efootprint/abstract_modeling_classes/explainable_hourly_quantities.py
efootprint/abstract_modeling_classes/explainable_object_base_class.py
efootprint/abstract_modeling_classes/explainable_object_dict.py
efootprint/abstract_modeling_classes/explainable_quantity.py
efootprint/abstract_modeling_classes/explainable_recurrent_quantities.py
efootprint/abstract_modeling_classes/explainable_timezone.py
efootprint/abstract_modeling_classes/list_linked_to_modeling_obj.py
efootprint/abstract_modeling_classes/modeling_object.py
efootprint/abstract_modeling_classes/modeling_update.py
efootprint/abstract_modeling_classes/object_linked_to_modeling_obj.py
efootprint/abstract_modeling_classes/source_objects.py
efootprint/abstract_modeling_classes/weighted_modeling_objects_dict.py
efootprint/all_classes_in_order.py
efootprint/api_utils/__init__.py
efootprint/api_utils/json_to_system.py
efootprint/api_utils/system_to_json.py
efootprint/api_utils/unit_mappings.py
efootprint/api_utils/version_upgrade_handlers.py
efootprint/builders/__init__.py
efootprint/builders/hardware/__init__.py
efootprint/builders/hardware/boavizta_cloud_server.py
efootprint/builders/hardware/boavizta_server_from_config.py
efootprint/builders/hardware/boaviztapi_utils.py
efootprint/builders/hardware/edge/__init__.py
efootprint/builders/hardware/edge/edge_appliance.py
efootprint/builders/hardware/edge/edge_computer.py
efootprint/builders/services/__init__.py
efootprint/builders/services/ecobenchmark_analysis/.gitignore
efootprint/builders/services/ecobenchmark_analysis/__init__.py
efootprint/builders/services/ecobenchmark_analysis/ecobenchmark_data_analysis.py
efootprint-14.0.2.dist-info/LICENSE
efootprint-14.0.2.dist-info/METADATA
efootprint-14.0.2.dist-info/WHEEL
efootprint-14.0.2.dist-info/RECORD
