Metadata-Version: 2.3
Name: efootprint
Version: 14.0.2
Summary: Digital service environmental footprint model
Author: Vincent Villet for Publicis Sapient
Requires-Python: >=3.12,<4.0
Classifier: Programming Language :: Python :: 3
Classifier: Programming Language :: Python :: 3.12
Classifier: Programming Language :: Python :: 3.13
Requires-Dist: boaviztapi (>=1,<2)
Requires-Dist: ciso8601 (>=2.3,<3.0)
Requires-Dist: ecologits (>=0.6,<0.7)
Requires-Dist: matplotlib (>=3.10,<4.0)
Requires-Dist: pandas (>=2,<3)
Requires-Dist: pint (>=0,<1)
Requires-Dist: plotly (==5.19)
Requires-Dist: pytz (==2024.1)
Requires-Dist: pyvis (==0.3.2)
Requires-Dist: requests (>=2.31,<3.0)
Requires-Dist: zstandard (>=0.23,<0.24)
